sdk/__init__.py
sdk/config_manager.py
sdk/sdk.py
sdk/utils.py
tests/__init__.py
tests/test_sdk.py
ml_tracking_sdk-0.1.1.dist-info/LICENSE
ml_tracking_sdk-0.1.1.dist-info/METADATA
ml_tracking_sdk-0.1.1.dist-info/WHEEL
ml_tracking_sdk-0.1.1.dist-info/top_level.txt
ml_tracking_sdk-0.1.1.dist-info/RECORD
