Metadata-Version: 2.1
Name: ml_tracking_sdk
Version: 0.1.1
Summary: A simplified MLflow SDK
Home-page: http://gitlab-paas.internal.sais.com.cn/data_intelligence_platform/mlflow_sdk
Author: Shepard
Author-email: shepard <zhaoxun@sais.com.cn>
License: MIT
Requires-Python: >=3.7
License-File: LICENSE
Requires-Dist: mlflow>=2.0.0
Requires-Dist: PyYAML>=6.0
Requires-Dist: scikit-learn>=1.2.0
